xlens/__init__.py
xlens/config.py
xlens/hooked_transformer.py
xlens/py.typed
xlens/utils.py
xlens/components/__init__.py
xlens/components/attention.py
xlens/components/embed.py
xlens/components/layer_norm.py
xlens/components/mlp.py
xlens/components/transformer_block.py
xlens/components/unembed.py
xlens/hooks/__init__.py
xlens/hooks/hook_point.py
xlens/hooks/utilities.py
xlens/pretrained/__init__.py
xlens/pretrained/convert.py
xlens/pretrained/model_converter.py
xlens/pretrained/converters/__init__.py
xlens/pretrained/converters/gpt2.py
xlens/pretrained/converters/llama.py
xlens/pretrained/converters/mistral.py
xlens/pretrained/converters/neox.py
xlens/pretrained/converters/qwen2.py
xlens/utilities/__init__.py
xlens/utilities/activation_functions.py
xlens-0.1.1.dist-info/METADATA
xlens-0.1.1.dist-info/WHEEL
xlens-0.1.1.dist-info/RECORD
