Metadata-Version: 2.3
Name: xlens
Version: 0.1.1
Summary: Add your description here
Requires-Python: ==3.12.*
Requires-Dist: einops>=0.8.0
Requires-Dist: equinox>=0.11.8
Requires-Dist: jax>=0.4.35
Requires-Dist: optax>=0.2.3
Requires-Dist: protobuf>=5.28.3
Requires-Dist: safetensors>=0.4.5
Requires-Dist: sentencepiece>=0.2.0
Requires-Dist: transformers>=4.46.1
